{"data":{"Year":[2019,2019,2019],"Observation status":["Normal value","Normal value","Normal value"],"Unit multiplier":["Units","Units","Units"],"SOURCE_DETAIL":["UNDRR_CPU","UNDRR_CPU","UNDRR_CPU"],"SERIES":["Number of directly affected persons attributed to disasters per 100,000 population [1.5.1, 11.5.1, 13.1.1]","Number of missing persons due to disaster [1.5.1, 11.5.1, 13.1.1]","Number of deaths due to disaster [1.5.1, 11.5.1, 13.1.1]"],"Reference area":[null,null,null],"UNIT_MEASURE":["Number","Number","Number"],"GeoCode":[null,null,null],"Value":[702363,344,344]},"edges":[]}