{"data":{"Year":[2022,2023,2024],"Observation status":["Normal value","Normal value","Normal value"],"Unit multiplier":["Units","Units","Units"],"SOURCE_DETAIL":["ZRP_Crime_Records","ZRP_Crime_Records","ZRP_Crime_Records"],"SERIES":["Proportion of population aged 18-29 years who experienced sexual violence by age\u00a018 [16.2.3]","Proportion of population aged 18-29 years who experienced sexual violence by age\u00a018 [16.2.3]","Proportion of population aged 18-29 years who experienced sexual violence by age\u00a018 [16.2.3]"],"Reference area":[null,null,null],"UNIT_MEASURE":["Percent","Percent","Percent"],"GeoCode":[null,null,null],"Value":[0.03,0.015,0.03]},"edges":[]}